{
  
  "Home": "Home",
  "AboutUS": "AboutUS",
  "Blog": "Blog",
  "Pages": "Pages",
  "Features": "Features",
  "ContactUS": "ContactUS",
  "DopDownName": "SHOP BY DEPARTMNET",
  "DropDownLinks": [
    "Action",
    "Best Seller Products",
    "Top 10 Offers",
    "New Arrivals",
    "Phone & Tablets",
    "Electronics & Digital",
    "Fashion & Clothings",
    "Jewelry & Watches",
    "Heath & Beauty",
    "TV & Audio",
    "Sound & Speaker",
    "Gadgets",
    "Toys & Hobbies",
    "Heath & Beauty",
    "Asus",
    "Acessories",
    "Art & Craft"
  ],
  "Hotline": "Hotline:",
  "Number": "(+100) 123 456 7890"

}
